rewards_envs/__init__.py
rewards_envs/core.py
rewards_envs/engines/pygame/__init__.py
rewards_envs/engines/pygame/car_race/__init__.py
rewards_envs/engines/pygame/car_race/assets/car.png
rewards_envs/engines/pygame/car_race/assets/evaluation/track-1.png
rewards_envs/engines/pygame/car_race/assets/training/track-1.png
rewards_envs/engines/pygame/car_race/assets/training/track-2.png
rewards_envs/engines/pygame/car_race/assets/training/track-3.png
rewards_envs/engines/pygame/car_race/car_race.py
rewards_envs/envs/__init__.py
rewards_envs/envs/car_race.py
rewards_envs-0.1.3.dist-info/METADATA
rewards_envs-0.1.3.dist-info/WHEEL
rewards_envs-0.1.3.dist-info/RECORD
